atom_metric_reporter-1.0.3.data/scripts/atom_metric_reporter
example/__init__.py
example/example.py
metric_reporter/__init__.py
metric_reporter/metric_reporter.py
metric_reporter/driver/__init__.py
metric_reporter/driver/appoptics.py
metric_reporter/driver/datadog.py
metric_reporter/driver/driver.py
metric_reporter/driver/driver_interface.py
metric_reporter/log/__init__.py
metric_reporter/log/log.py
metric_reporter/log/log_interface.py
metric_reporter/thread_pool/__init__.py
metric_reporter/thread_pool/thread_pool.py
test/__init__.py
test/driver_test.py
test/metric_reporter_test.py
atom_metric_reporter-1.0.3.dist-info/LICENSE
atom_metric_reporter-1.0.3.dist-info/METADATA
atom_metric_reporter-1.0.3.dist-info/WHEEL
atom_metric_reporter-1.0.3.dist-info/top_level.txt
atom_metric_reporter-1.0.3.dist-info/RECORD
