Metadata-Version: 2.1
Name: atom-metric-reporter
Version: 1.0.3
Summary: Atom Metric Reporter
Home-page: https://github.com/infrasrc/atom-metric-reporter-python
Author: g8y3e
Author-email: valentine.pavchuk@ironsrc.com
License: UNKNOWN
Platform: UNKNOWN
Classifier: Programming Language :: Python :: 2.7
Classifier: License :: OSI Approved :: MIT License
Classifier: Operating System :: OS Independent
